doz/__init__.py
doz/doz.py
doz/fdz.py
doz/gpts-int.py
doz/helpers.py
doz/used.py
doz-1.0.0.dist-info/LICENSE
doz-1.0.0.dist-info/METADATA
doz-1.0.0.dist-info/WHEEL
doz-1.0.0.dist-info/top_level.txt
doz-1.0.0.dist-info/RECORD
