Metadata-Version: 2.2
Name: doz
Version: 1.0.0
Summary: Dozenal Type for Python
License: MIT
Project-URL: Homepage, https://github.com/islekcaganmert/doz
Requires-Python: >=3.11
License-File: LICENSE
